README.md
setup.py
ZmUser.egg-info/PKG-INFO
ZmUser.egg-info/SOURCES.txt
ZmUser.egg-info/dependency_links.txt
ZmUser.egg-info/requires.txt
ZmUser.egg-info/top_level.txt
sample/__init__.py
sample/app.py
sample/run.py
zm_user/__init__.py
zm_user/conf.py
zm_user/models/__init__.py
zm_user/models/base.py
zm_user/models/permission.py
zm_user/models/platform.py
zm_user/models/platform_user.py
zm_user/models/role.py
zm_user/models/unit.py
zm_user/models/user.py
zm_user/tools/__init__.py
zm_user/tools/jsonify.py
zm_user/tools/params.py
zm_user/tools/permission.py
zm_user/tools/string_help.py
zm_user/tools/time.py
zm_user/views/__init__.py
zm_user/views/bb.py
zm_user/views/platform.py
zm_user/views/role.py
zm_user/views/unit.py
zm_user/views/user.py